{
  "body": "_from README.md_\r\n\r\n *  Searching for an operator name returns the documentation for\r\n    the operator.  (`p6doc '%%'`  returns the documentation for\r\n    `&infix:<%%>`.)\r\n\r\nNote - this already works in the web search.\r\n\r\n",
  "author_association": "OWNER",
  "assignees": [
    
  ],
  "assignee": null,
  "closed_by": null,
  "updated_at": "2016-12-28T19:38:07Z",
  "created_at": "2016-12-28T19:38:07Z",
  "comments_url": "https://api.github.com/repos/perl6/doc/issues/1088/comments",
  "locked": false,
  "title": "Search for operator name with p6doc",
  "id": 197905238,
  "html_url": "https://github.com/perl6/doc/issues/1088",
  "closed_at": null,
  "milestone": null,
  "state": "open",
  "labels_url": "https://api.github.com/repos/perl6/doc/issues/1088/labels{/name}",
  "number": 1088,
  "comments": 0,
  "labels": [
    {
      "color": "fef2c0",
      "name": "wishlist",
      "id": 493345410,
      "default": false,
      "url": "https://api.github.com/repos/perl6/doc/labels/wishlist"
    }
  ],
  "events_url": "https://api.github.com/repos/perl6/doc/issues/1088/events",
  "user": {
    "following_url": "https://api.github.com/users/coke/following{/other_user}",
    "gists_url": "https://api.github.com/users/coke/gists{/gist_id}",
    "received_events_url": "https://api.github.com/users/coke/received_events",
    "organizations_url": "https://api.github.com/users/coke/orgs",
    "subscriptions_url": "https://api.github.com/users/coke/subscriptions",
    "html_url": "https://github.com/coke",
    "id": 50257,
    "login": "coke",
    "type": "User",
    "repos_url": "https://api.github.com/users/coke/repos",
    "site_admin": false,
    "events_url": "https://api.github.com/users/coke/events{/privacy}",
    "gravatar_id": "",
    "avatar_url": "https://avatars3.githubusercontent.com/u/50257?v=4",
    "starred_url": "https://api.github.com/users/coke/starred{/owner}{/repo}",
    "followers_url": "https://api.github.com/users/coke/followers",
    "url": "https://api.github.com/users/coke"
  },
  "repository_url": "https://api.github.com/repos/perl6/doc",
  "url": "https://api.github.com/repos/perl6/doc/issues/1088"
}