{
  "body": "This issue was mentioned a couple of times. ``∖`` and ``\\`` are visually too similar. Worse, sometimes they are even rendered identically. But this is not the only case, there are many non-ascii characters that look like something else. How to deal with this stuff?\r\n\r\nAs an example, here are some screenshots of how it's rendered for me:\r\n\r\nEmacs:\r\n![emacs screenshot](https://user-images.githubusercontent.com/5507503/29181733-e55bb6d8-7e04-11e7-96b2-41124a5e5d9a.png)\r\n\r\nFirefox:\r\n![firefox screenshot](https://user-images.githubusercontent.com/5507503/29181934-9f1f22b2-7e05-11e7-92c8-5f05c52ade8f.png)\r\n\r\nYou'll notice that my emacs screenshot clearly shows that these characters are different. However, there's nothing clever about this:\r\n> my recommendation is really stupid. I'm using bitmap fonts for everything, these typically don't have the whole unicode range, so it falls back to any font that the system has with that glyph. This way, ascii range renders sharp and everything else is noticeably blurry\r\n\r\n\r\nAnyway, I think that the proper solution would be to configure your editor to highlight characters out of ascii range (similarly to how people highlight whitespace). After some experiments I'll write about it.",
  "author_association": "MEMBER",
  "assignees": [
    {
      "following_url": "https://api.github.com/users/AlexDaniel/following{/other_user}",
      "gists_url": "https://api.github.com/users/AlexDaniel/gists{/gist_id}",
      "received_events_url": "https://api.github.com/users/AlexDaniel/received_events",
      "organizations_url": "https://api.github.com/users/AlexDaniel/orgs",
      "subscriptions_url": "https://api.github.com/users/AlexDaniel/subscriptions",
      "html_url": "https://github.com/AlexDaniel",
      "id": 5507503,
      "login": "AlexDaniel",
      "type": "User",
      "repos_url": "https://api.github.com/users/AlexDaniel/repos",
      "site_admin": false,
      "events_url": "https://api.github.com/users/AlexDaniel/events{/privacy}",
      "gravatar_id": "",
      "avatar_url": "https://avatars3.githubusercontent.com/u/5507503?v=4",
      "starred_url": "https://api.github.com/users/AlexDaniel/starred{/owner}{/repo}",
      "followers_url": "https://api.github.com/users/AlexDaniel/followers",
      "url": "https://api.github.com/users/AlexDaniel"
    }
  ],
  "assignee": {
    "following_url": "https://api.github.com/users/AlexDaniel/following{/other_user}",
    "gists_url": "https://api.github.com/users/AlexDaniel/gists{/gist_id}",
    "received_events_url": "https://api.github.com/users/AlexDaniel/received_events",
    "organizations_url": "https://api.github.com/users/AlexDaniel/orgs",
    "subscriptions_url": "https://api.github.com/users/AlexDaniel/subscriptions",
    "html_url": "https://github.com/AlexDaniel",
    "id": 5507503,
    "login": "AlexDaniel",
    "type": "User",
    "repos_url": "https://api.github.com/users/AlexDaniel/repos",
    "site_admin": false,
    "events_url": "https://api.github.com/users/AlexDaniel/events{/privacy}",
    "gravatar_id": "",
    "avatar_url": "https://avatars3.githubusercontent.com/u/5507503?v=4",
    "starred_url": "https://api.github.com/users/AlexDaniel/starred{/owner}{/repo}",
    "followers_url": "https://api.github.com/users/AlexDaniel/followers",
    "url": "https://api.github.com/users/AlexDaniel"
  },
  "closed_by": null,
  "updated_at": "2018-03-28T08:56:43Z",
  "created_at": "2017-08-10T16:59:40Z",
  "comments_url": "https://api.github.com/repos/perl6/doc/issues/1444/comments",
  "locked": false,
  "title": "FAQ/unicode_entry Unicode characters that look alike",
  "id": 249412975,
  "html_url": "https://github.com/perl6/doc/issues/1444",
  "closed_at": null,
  "milestone": null,
  "state": "open",
  "labels_url": "https://api.github.com/repos/perl6/doc/issues/1444/labels{/name}",
  "number": 1444,
  "comments": 6,
  "labels": [
    {
      "color": "fef2c0",
      "name": "wishlist",
      "id": 493345410,
      "default": false,
      "url": "https://api.github.com/repos/perl6/doc/labels/wishlist"
    }
  ],
  "events_url": "https://api.github.com/repos/perl6/doc/issues/1444/events",
  "user": {
    "following_url": "https://api.github.com/users/AlexDaniel/following{/other_user}",
    "gists_url": "https://api.github.com/users/AlexDaniel/gists{/gist_id}",
    "received_events_url": "https://api.github.com/users/AlexDaniel/received_events",
    "organizations_url": "https://api.github.com/users/AlexDaniel/orgs",
    "subscriptions_url": "https://api.github.com/users/AlexDaniel/subscriptions",
    "html_url": "https://github.com/AlexDaniel",
    "id": 5507503,
    "login": "AlexDaniel",
    "type": "User",
    "repos_url": "https://api.github.com/users/AlexDaniel/repos",
    "site_admin": false,
    "events_url": "https://api.github.com/users/AlexDaniel/events{/privacy}",
    "gravatar_id": "",
    "avatar_url": "https://avatars3.githubusercontent.com/u/5507503?v=4",
    "starred_url": "https://api.github.com/users/AlexDaniel/starred{/owner}{/repo}",
    "followers_url": "https://api.github.com/users/AlexDaniel/followers",
    "url": "https://api.github.com/users/AlexDaniel"
  },
  "repository_url": "https://api.github.com/repos/perl6/doc",
  "url": "https://api.github.com/repos/perl6/doc/issues/1444"
}