{
  "body": "Specify whether the endpoints are included or not when selecting the\r\npseudo-random number.\r\n\r\nReferences:\r\n\r\n- https://github.com/perl6/roast/blob/master/S32-num/rand.t#L13-L30\r\n- https://github.com/MoarVM/MoarVM/blob/master/3rdparty/tinymt/tinymt64.c#L97-L116\r\n\r\nFixes #787.",
  "pull_request": {
    "html_url": "https://github.com/perl6/doc/pull/1498",
    "url": "https://api.github.com/repos/perl6/doc/pulls/1498",
    "diff_url": "https://github.com/perl6/doc/pull/1498.diff",
    "patch_url": "https://github.com/perl6/doc/pull/1498.patch"
  },
  "author_association": "MEMBER",
  "milestone": null,
  "html_url": "https://github.com/perl6/doc/pull/1498",
  "events_url": "https://api.github.com/repos/perl6/doc/issues/1498/events",
  "url": "https://api.github.com/repos/perl6/doc/issues/1498",
  "state": "closed",
  "labels": [
    
  ],
  "title": "Clear ambiguity regarding Int/Real rand()",
  "labels_url": "https://api.github.com/repos/perl6/doc/issues/1498/labels{/name}",
  "closed_at": "2017-09-02T09:36:59Z",
  "assignees": [
    
  ],
  "locked": false,
  "repository_url": "https://api.github.com/repos/perl6/doc",
  "closed_by": {
    "events_url": "https://api.github.com/users/Altai-man/events{/privacy}",
    "following_url": "https://api.github.com/users/Altai-man/following{/other_user}",
    "followers_url": "https://api.github.com/users/Altai-man/followers",
    "html_url": "https://github.com/Altai-man",
    "url": "https://api.github.com/users/Altai-man",
    "site_admin": false,
    "type": "User",
    "organizations_url": "https://api.github.com/users/Altai-man/orgs",
    "gists_url": "https://api.github.com/users/Altai-man/gists{/gist_id}",
    "avatar_url": "https://avatars1.githubusercontent.com/u/5764435?v=4",
    "id": 5764435,
    "starred_url": "https://api.github.com/users/Altai-man/starred{/owner}{/repo}",
    "received_events_url": "https://api.github.com/users/Altai-man/received_events",
    "gravatar_id": "",
    "repos_url": "https://api.github.com/users/Altai-man/repos",
    "subscriptions_url": "https://api.github.com/users/Altai-man/subscriptions",
    "node_id": "MDQ6VXNlcjU3NjQ0MzU=",
    "login": "Altai-man"
  },
  "comments": 2,
  "user": {
    "events_url": "https://api.github.com/users/zakame/events{/privacy}",
    "following_url": "https://api.github.com/users/zakame/following{/other_user}",
    "followers_url": "https://api.github.com/users/zakame/followers",
    "html_url": "https://github.com/zakame",
    "url": "https://api.github.com/users/zakame",
    "site_admin": false,
    "type": "User",
    "organizations_url": "https://api.github.com/users/zakame/orgs",
    "gists_url": "https://api.github.com/users/zakame/gists{/gist_id}",
    "avatar_url": "https://avatars3.githubusercontent.com/u/110625?v=4",
    "id": 110625,
    "starred_url": "https://api.github.com/users/zakame/starred{/owner}{/repo}",
    "received_events_url": "https://api.github.com/users/zakame/received_events",
    "gravatar_id": "",
    "repos_url": "https://api.github.com/users/zakame/repos",
    "subscriptions_url": "https://api.github.com/users/zakame/subscriptions",
    "node_id": "MDQ6VXNlcjExMDYyNQ==",
    "login": "zakame"
  },
  "id": 254799319,
  "updated_at": "2017-09-02T09:38:23Z",
  "assignee": null,
  "created_at": "2017-09-02T08:50:54Z",
  "number": 1498,
  "comments_url": "https://api.github.com/repos/perl6/doc/issues/1498/comments",
  "node_id": "MDExOlB1bGxSZXF1ZXN0MTM5MDA1NDg4"
}