{
  "body": "The settings in the modeline do the following:\r\n\r\n* Highlight this file as Perl6\r\n* Expand tabs into 4 spaces\r\n\r\nThis is helpful for vim users for highlighting an atypical file format\r\nand creates formatting consistency with regards to tabs and spacing.",
  "pull_request": {
    "html_url": "https://github.com/perl6/doc/pull/1661",
    "url": "https://api.github.com/repos/perl6/doc/pulls/1661",
    "diff_url": "https://github.com/perl6/doc/pull/1661.diff",
    "patch_url": "https://github.com/perl6/doc/pull/1661.patch"
  },
  "author_association": "MEMBER",
  "milestone": null,
  "html_url": "https://github.com/perl6/doc/pull/1661",
  "events_url": "https://api.github.com/repos/perl6/doc/issues/1661/events",
  "url": "https://api.github.com/repos/perl6/doc/issues/1661",
  "state": "closed",
  "labels": [
    
  ],
  "title": "Add vim modeline at end of every file without one",
  "labels_url": "https://api.github.com/repos/perl6/doc/issues/1661/labels{/name}",
  "closed_at": "2017-11-06T03:37:20Z",
  "assignees": [
    
  ],
  "locked": false,
  "repository_url": "https://api.github.com/repos/perl6/doc",
  "closed_by": {
    "events_url": "https://api.github.com/users/jstuder-gh/events{/privacy}",
    "following_url": "https://api.github.com/users/jstuder-gh/following{/other_user}",
    "followers_url": "https://api.github.com/users/jstuder-gh/followers",
    "html_url": "https://github.com/jstuder-gh",
    "url": "https://api.github.com/users/jstuder-gh",
    "site_admin": false,
    "type": "User",
    "organizations_url": "https://api.github.com/users/jstuder-gh/orgs",
    "gists_url": "https://api.github.com/users/jstuder-gh/gists{/gist_id}",
    "avatar_url": "https://avatars0.githubusercontent.com/u/10088878?v=4",
    "id": 10088878,
    "starred_url": "https://api.github.com/users/jstuder-gh/starred{/owner}{/repo}",
    "received_events_url": "https://api.github.com/users/jstuder-gh/received_events",
    "gravatar_id": "",
    "repos_url": "https://api.github.com/users/jstuder-gh/repos",
    "subscriptions_url": "https://api.github.com/users/jstuder-gh/subscriptions",
    "node_id": "MDQ6VXNlcjEwMDg4ODc4",
    "login": "jstuder-gh"
  },
  "comments": 6,
  "user": {
    "events_url": "https://api.github.com/users/jstuder-gh/events{/privacy}",
    "following_url": "https://api.github.com/users/jstuder-gh/following{/other_user}",
    "followers_url": "https://api.github.com/users/jstuder-gh/followers",
    "html_url": "https://github.com/jstuder-gh",
    "url": "https://api.github.com/users/jstuder-gh",
    "site_admin": false,
    "type": "User",
    "organizations_url": "https://api.github.com/users/jstuder-gh/orgs",
    "gists_url": "https://api.github.com/users/jstuder-gh/gists{/gist_id}",
    "avatar_url": "https://avatars0.githubusercontent.com/u/10088878?v=4",
    "id": 10088878,
    "starred_url": "https://api.github.com/users/jstuder-gh/starred{/owner}{/repo}",
    "received_events_url": "https://api.github.com/users/jstuder-gh/received_events",
    "gravatar_id": "",
    "repos_url": "https://api.github.com/users/jstuder-gh/repos",
    "subscriptions_url": "https://api.github.com/users/jstuder-gh/subscriptions",
    "node_id": "MDQ6VXNlcjEwMDg4ODc4",
    "login": "jstuder-gh"
  },
  "id": 271304492,
  "updated_at": "2017-11-06T05:00:03Z",
  "assignee": null,
  "created_at": "2017-11-05T18:58:44Z",
  "number": 1661,
  "comments_url": "https://api.github.com/repos/perl6/doc/issues/1661/comments",
  "node_id": "MDExOlB1bGxSZXF1ZXN0MTUwNzM2NzAx"
}