{
  "body": "Only https://design.perl6.org/S05.html mentions it.",
  "author_association": "MEMBER",
  "assignees": [
    
  ],
  "assignee": null,
  "node_id": "MDU6SXNzdWUyOTUyOTAwNTU=",
  "closed_by": null,
  "updated_at": "2018-02-20T02:23:40Z",
  "created_at": "2018-02-07T20:57:36Z",
  "comments_url": "https://api.github.com/repos/perl6/doc/issues/1760/comments",
  "locked": false,
  "title": "Special variable `$¢` (Cursor) is not documented",
  "id": 295290055,
  "html_url": "https://github.com/perl6/doc/issues/1760",
  "closed_at": null,
  "milestone": null,
  "state": "open",
  "labels_url": "https://api.github.com/repos/perl6/doc/issues/1760/labels{/name}",
  "number": 1760,
  "comments": 7,
  "labels": [
    {
      "color": "5DE0FA",
      "name": "NOTSPECCED",
      "node_id": "MDU6TGFiZWw0MjAwOTI1MjI=",
      "id": 420092522,
      "default": false,
      "url": "https://api.github.com/repos/perl6/doc/labels/NOTSPECCED"
    },
    {
      "color": "5DE0FA",
      "name": "docs",
      "node_id": "MDU6TGFiZWwyNDQ4NDMyMjU=",
      "id": 244843225,
      "default": false,
      "url": "https://api.github.com/repos/perl6/doc/labels/docs"
    }
  ],
  "events_url": "https://api.github.com/repos/perl6/doc/issues/1760/events",
  "user": {
    "following_url": "https://api.github.com/users/samcv/following{/other_user}",
    "node_id": "MDQ6VXNlcjIwMTQ1NTU3",
    "gists_url": "https://api.github.com/users/samcv/gists{/gist_id}",
    "received_events_url": "https://api.github.com/users/samcv/received_events",
    "organizations_url": "https://api.github.com/users/samcv/orgs",
    "subscriptions_url": "https://api.github.com/users/samcv/subscriptions",
    "html_url": "https://github.com/samcv",
    "id": 20145557,
    "login": "samcv",
    "type": "User",
    "repos_url": "https://api.github.com/users/samcv/repos",
    "site_admin": false,
    "events_url": "https://api.github.com/users/samcv/events{/privacy}",
    "gravatar_id": "",
    "avatar_url": "https://avatars1.githubusercontent.com/u/20145557?v=4",
    "starred_url": "https://api.github.com/users/samcv/starred{/owner}{/repo}",
    "followers_url": "https://api.github.com/users/samcv/followers",
    "url": "https://api.github.com/users/samcv"
  },
  "repository_url": "https://api.github.com/repos/perl6/doc",
  "url": "https://api.github.com/repos/perl6/doc/issues/1760"
}