{
  "body": "## The problem\r\n\r\nIt seems that substitions using uppercase S instead of s (return string with substitutions instead of modifying in place) is not documented.\r\n\r\n## Suggestions\r\n\r\nAdd documentation for S to the regex overview page (https://docs.perl6.org/language/regexes)\r\n\r\nEDIT: I was just told about the documentation [here](https://docs.perl6.org/language/operators#S///_non-destructive_substitution). But it probably wouldn't hurt to mention it on the regex page.",
  "author_association": "MEMBER",
  "assignees": [
    
  ],
  "assignee": null,
  "node_id": "MDU6SXNzdWUzMTcxNzE0NTc=",
  "closed_by": {
    "following_url": "https://api.github.com/users/zoffixznet/following{/other_user}",
    "node_id": "MDQ6VXNlcjU3NDc5MTg=",
    "gists_url": "https://api.github.com/users/zoffixznet/gists{/gist_id}",
    "received_events_url": "https://api.github.com/users/zoffixznet/received_events",
    "organizations_url": "https://api.github.com/users/zoffixznet/orgs",
    "subscriptions_url": "https://api.github.com/users/zoffixznet/subscriptions",
    "html_url": "https://github.com/zoffixznet",
    "id": 5747918,
    "login": "zoffixznet",
    "type": "User",
    "repos_url": "https://api.github.com/users/zoffixznet/repos",
    "site_admin": false,
    "events_url": "https://api.github.com/users/zoffixznet/events{/privacy}",
    "gravatar_id": "",
    "avatar_url": "https://avatars2.githubusercontent.com/u/5747918?v=4",
    "starred_url": "https://api.github.com/users/zoffixznet/starred{/owner}{/repo}",
    "followers_url": "https://api.github.com/users/zoffixznet/followers",
    "url": "https://api.github.com/users/zoffixznet"
  },
  "updated_at": "2018-04-27T20:15:21Z",
  "created_at": "2018-04-24T10:48:39Z",
  "comments_url": "https://api.github.com/repos/perl6/doc/issues/1959/comments",
  "locked": false,
  "title": "S/// not indexed",
  "id": 317171457,
  "html_url": "https://github.com/perl6/doc/issues/1959",
  "closed_at": "2018-04-27T20:15:21Z",
  "milestone": null,
  "state": "closed",
  "labels_url": "https://api.github.com/repos/perl6/doc/issues/1959/labels{/name}",
  "number": 1959,
  "comments": 2,
  "labels": [
    {
      "color": "b60205",
      "name": "bug",
      "node_id": "MDU6TGFiZWw2NzY4MTQwMjM=",
      "id": 676814023,
      "default": true,
      "url": "https://api.github.com/repos/perl6/doc/labels/bug"
    }
  ],
  "events_url": "https://api.github.com/repos/perl6/doc/issues/1959/events",
  "user": {
    "following_url": "https://api.github.com/users/jkramer/following{/other_user}",
    "node_id": "MDQ6VXNlcjY5OTk=",
    "gists_url": "https://api.github.com/users/jkramer/gists{/gist_id}",
    "received_events_url": "https://api.github.com/users/jkramer/received_events",
    "organizations_url": "https://api.github.com/users/jkramer/orgs",
    "subscriptions_url": "https://api.github.com/users/jkramer/subscriptions",
    "html_url": "https://github.com/jkramer",
    "id": 6999,
    "login": "jkramer",
    "type": "User",
    "repos_url": "https://api.github.com/users/jkramer/repos",
    "site_admin": false,
    "events_url": "https://api.github.com/users/jkramer/events{/privacy}",
    "gravatar_id": "",
    "avatar_url": "https://avatars0.githubusercontent.com/u/6999?v=4",
    "starred_url": "https://api.github.com/users/jkramer/starred{/owner}{/repo}",
    "followers_url": "https://api.github.com/users/jkramer/followers",
    "url": "https://api.github.com/users/jkramer"
  },
  "repository_url": "https://api.github.com/repos/perl6/doc",
  "url": "https://api.github.com/repos/perl6/doc/issues/1959"
}