{
  "body": "## The problem\r\n\r\nDocumentation of [X::NYI](https://docs.perl6.org/type/X::NYI) says that it inherits from Exception.\r\n\r\nSo natural assumption is to write:\r\n```perl6\r\nX::NYI.new( message => \"Making coffee\" ).throw( )\r\n```\r\n\r\nWhich gives incomplete error message:\r\n```\r\n not yet implemented. Sorry.\r\n```\r\n\r\nWhile in fact undocumented `feature` param must be used:\r\n```perl6\r\nX::NYI.new( feature => \"Making coffee\" ).throw( )\r\n```\r\n```\r\nMaking coffee not yet implemented. Sorry.\r\n```\r\n\r\n## Suggestions\r\n\r\nParam `feature` should be documented.",
  "author_association": "MEMBER",
  "assignees": [
    
  ],
  "assignee": null,
  "node_id": "MDU6SXNzdWUzMjU5ODg1OTY=",
  "closed_by": {
    "following_url": "https://api.github.com/users/JJ/following{/other_user}",
    "node_id": "MDQ6VXNlcjUwMA==",
    "gists_url": "https://api.github.com/users/JJ/gists{/gist_id}",
    "received_events_url": "https://api.github.com/users/JJ/received_events",
    "organizations_url": "https://api.github.com/users/JJ/orgs",
    "subscriptions_url": "https://api.github.com/users/JJ/subscriptions",
    "html_url": "https://github.com/JJ",
    "id": 500,
    "login": "JJ",
    "type": "User",
    "repos_url": "https://api.github.com/users/JJ/repos",
    "site_admin": false,
    "events_url": "https://api.github.com/users/JJ/events{/privacy}",
    "gravatar_id": "",
    "avatar_url": "https://avatars3.githubusercontent.com/u/500?v=4",
    "starred_url": "https://api.github.com/users/JJ/starred{/owner}{/repo}",
    "followers_url": "https://api.github.com/users/JJ/followers",
    "url": "https://api.github.com/users/JJ"
  },
  "updated_at": "2018-05-24T17:50:16Z",
  "created_at": "2018-05-24T07:01:11Z",
  "comments_url": "https://api.github.com/repos/perl6/doc/issues/2052/comments",
  "locked": false,
  "title": "X::NYI - insufficient info about construction params.",
  "id": 325988596,
  "html_url": "https://github.com/perl6/doc/issues/2052",
  "closed_at": "2018-05-24T07:52:39Z",
  "milestone": null,
  "state": "closed",
  "labels_url": "https://api.github.com/repos/perl6/doc/issues/2052/labels{/name}",
  "number": 2052,
  "comments": 2,
  "labels": [
    {
      "color": "5DE0FA",
      "name": "docs",
      "node_id": "MDU6TGFiZWwyNDQ4NDMyMjU=",
      "id": 244843225,
      "default": false,
      "url": "https://api.github.com/repos/perl6/doc/labels/docs"
    },
    {
      "color": "5DE0FA",
      "name": "update",
      "node_id": "MDU6TGFiZWw2NzY4MDA2NzY=",
      "id": 676800676,
      "default": false,
      "url": "https://api.github.com/repos/perl6/doc/labels/update"
    }
  ],
  "events_url": "https://api.github.com/repos/perl6/doc/issues/2052/events",
  "user": {
    "following_url": "https://api.github.com/users/bbkr/following{/other_user}",
    "node_id": "MDQ6VXNlcjE1NzUwMA==",
    "gists_url": "https://api.github.com/users/bbkr/gists{/gist_id}",
    "received_events_url": "https://api.github.com/users/bbkr/received_events",
    "organizations_url": "https://api.github.com/users/bbkr/orgs",
    "subscriptions_url": "https://api.github.com/users/bbkr/subscriptions",
    "html_url": "https://github.com/bbkr",
    "id": 157500,
    "login": "bbkr",
    "type": "User",
    "repos_url": "https://api.github.com/users/bbkr/repos",
    "site_admin": false,
    "events_url": "https://api.github.com/users/bbkr/events{/privacy}",
    "gravatar_id": "",
    "avatar_url": "https://avatars0.githubusercontent.com/u/157500?v=4",
    "starred_url": "https://api.github.com/users/bbkr/starred{/owner}{/repo}",
    "followers_url": "https://api.github.com/users/bbkr/followers",
    "url": "https://api.github.com/users/bbkr"
  },
  "repository_url": "https://api.github.com/repos/perl6/doc",
  "url": "https://api.github.com/repos/perl6/doc/issues/2052"
}