{
  "body": "## The problem\r\n\r\nhttps://github.com/perl6/doc/blob/e8f96f158e3cd552c5b594c1de770f3182f09547/doc/Language/classtut.pod6#L36\r\n\r\nrenders badly on https://docs.perl6.org/language/classtut\r\n\r\n## Suggestions\r\n\r\ni have no idea how to fix this",
  "author_association": "MEMBER",
  "milestone": null,
  "html_url": "https://github.com/perl6/doc/issues/2151",
  "events_url": "https://api.github.com/repos/perl6/doc/issues/2151/events",
  "url": "https://api.github.com/repos/perl6/doc/issues/2151",
  "state": "closed",
  "labels": [
    
  ],
  "title": "classtut rendering broken",
  "labels_url": "https://api.github.com/repos/perl6/doc/issues/2151/labels{/name}",
  "closed_at": "2018-07-06T10:51:30Z",
  "assignees": [
    
  ],
  "locked": false,
  "repository_url": "https://api.github.com/repos/perl6/doc",
  "closed_by": {
    "events_url": "https://api.github.com/users/JJ/events{/privacy}",
    "following_url": "https://api.github.com/users/JJ/following{/other_user}",
    "followers_url": "https://api.github.com/users/JJ/followers",
    "html_url": "https://github.com/JJ",
    "url": "https://api.github.com/users/JJ",
    "site_admin": false,
    "type": "User",
    "organizations_url": "https://api.github.com/users/JJ/orgs",
    "gists_url": "https://api.github.com/users/JJ/gists{/gist_id}",
    "avatar_url": "https://avatars3.githubusercontent.com/u/500?v=4",
    "id": 500,
    "starred_url": "https://api.github.com/users/JJ/starred{/owner}{/repo}",
    "received_events_url": "https://api.github.com/users/JJ/received_events",
    "gravatar_id": "",
    "repos_url": "https://api.github.com/users/JJ/repos",
    "subscriptions_url": "https://api.github.com/users/JJ/subscriptions",
    "node_id": "MDQ6VXNlcjUwMA==",
    "login": "JJ"
  },
  "comments": 1,
  "user": {
    "events_url": "https://api.github.com/users/eiro/events{/privacy}",
    "following_url": "https://api.github.com/users/eiro/following{/other_user}",
    "followers_url": "https://api.github.com/users/eiro/followers",
    "html_url": "https://github.com/eiro",
    "url": "https://api.github.com/users/eiro",
    "site_admin": false,
    "type": "User",
    "organizations_url": "https://api.github.com/users/eiro/orgs",
    "gists_url": "https://api.github.com/users/eiro/gists{/gist_id}",
    "avatar_url": "https://avatars0.githubusercontent.com/u/150884?v=4",
    "id": 150884,
    "starred_url": "https://api.github.com/users/eiro/starred{/owner}{/repo}",
    "received_events_url": "https://api.github.com/users/eiro/received_events",
    "gravatar_id": "",
    "repos_url": "https://api.github.com/users/eiro/repos",
    "subscriptions_url": "https://api.github.com/users/eiro/subscriptions",
    "node_id": "MDQ6VXNlcjE1MDg4NA==",
    "login": "eiro"
  },
  "id": 338858912,
  "updated_at": "2018-07-06T10:51:30Z",
  "assignee": null,
  "created_at": "2018-07-06T08:55:37Z",
  "number": 2151,
  "comments_url": "https://api.github.com/repos/perl6/doc/issues/2151/comments",
  "node_id": "MDU6SXNzdWUzMzg4NTg5MTI="
}