{
  "body": "I also changed a few words in Emacs section. Hope that's OK.\n",
  "author_association": "MEMBER",
  "assignees": [
    
  ],
  "assignee": null,
  "closed_by": {
    "following_url": "https://api.github.com/users/moritz/following{/other_user}",
    "gists_url": "https://api.github.com/users/moritz/gists{/gist_id}",
    "received_events_url": "https://api.github.com/users/moritz/received_events",
    "organizations_url": "https://api.github.com/users/moritz/orgs",
    "subscriptions_url": "https://api.github.com/users/moritz/subscriptions",
    "html_url": "https://github.com/moritz",
    "id": 23773,
    "login": "moritz",
    "type": "User",
    "repos_url": "https://api.github.com/users/moritz/repos",
    "site_admin": false,
    "events_url": "https://api.github.com/users/moritz/events{/privacy}",
    "gravatar_id": "",
    "avatar_url": "https://avatars1.githubusercontent.com/u/23773?v=4",
    "starred_url": "https://api.github.com/users/moritz/starred{/owner}{/repo}",
    "followers_url": "https://api.github.com/users/moritz/followers",
    "url": "https://api.github.com/users/moritz"
  },
  "updated_at": "2016-01-07T06:54:23Z",
  "created_at": "2016-01-06T19:55:50Z",
  "comments_url": "https://api.github.com/repos/perl6/doc/issues/321/comments",
  "pull_request": {
    "html_url": "https://github.com/perl6/doc/pull/321",
    "diff_url": "https://github.com/perl6/doc/pull/321.diff",
    "patch_url": "https://github.com/perl6/doc/pull/321.patch",
    "url": "https://api.github.com/repos/perl6/doc/pulls/321"
  },
  "locked": false,
  "title": "Add another way of entering unicode characters in Emacs",
  "id": 125250127,
  "html_url": "https://github.com/perl6/doc/pull/321",
  "closed_at": "2016-01-06T20:00:31Z",
  "milestone": null,
  "state": "closed",
  "labels_url": "https://api.github.com/repos/perl6/doc/issues/321/labels{/name}",
  "number": 321,
  "comments": 2,
  "labels": [
    
  ],
  "events_url": "https://api.github.com/repos/perl6/doc/issues/321/events",
  "user": {
    "following_url": "https://api.github.com/users/CIAvash/following{/other_user}",
    "gists_url": "https://api.github.com/users/CIAvash/gists{/gist_id}",
    "received_events_url": "https://api.github.com/users/CIAvash/received_events",
    "organizations_url": "https://api.github.com/users/CIAvash/orgs",
    "subscriptions_url": "https://api.github.com/users/CIAvash/subscriptions",
    "html_url": "https://github.com/CIAvash",
    "id": 1062270,
    "login": "CIAvash",
    "type": "User",
    "repos_url": "https://api.github.com/users/CIAvash/repos",
    "site_admin": false,
    "events_url": "https://api.github.com/users/CIAvash/events{/privacy}",
    "gravatar_id": "",
    "avatar_url": "https://avatars1.githubusercontent.com/u/1062270?v=4",
    "starred_url": "https://api.github.com/users/CIAvash/starred{/owner}{/repo}",
    "followers_url": "https://api.github.com/users/CIAvash/followers",
    "url": "https://api.github.com/users/CIAvash"
  },
  "repository_url": "https://api.github.com/repos/perl6/doc",
  "url": "https://api.github.com/repos/perl6/doc/issues/321"
}