{
  "body": "Example should use $.b to demonstrate method calls to $.a\n",
  "author_association": "MEMBER",
  "assignees": [
    
  ],
  "assignee": null,
  "node_id": "MDExOlB1bGxSZXF1ZXN0MzMwMTgyNDE=",
  "closed_by": {
    "following_url": "https://api.github.com/users/paultcochrane/following{/other_user}",
    "node_id": "MDQ6VXNlcjM0MzcyNjM=",
    "gists_url": "https://api.github.com/users/paultcochrane/gists{/gist_id}",
    "received_events_url": "https://api.github.com/users/paultcochrane/received_events",
    "organizations_url": "https://api.github.com/users/paultcochrane/orgs",
    "subscriptions_url": "https://api.github.com/users/paultcochrane/subscriptions",
    "html_url": "https://github.com/paultcochrane",
    "id": 3437263,
    "login": "paultcochrane",
    "type": "User",
    "repos_url": "https://api.github.com/users/paultcochrane/repos",
    "site_admin": false,
    "events_url": "https://api.github.com/users/paultcochrane/events{/privacy}",
    "gravatar_id": "",
    "avatar_url": "https://avatars0.githubusercontent.com/u/3437263?v=4",
    "starred_url": "https://api.github.com/users/paultcochrane/starred{/owner}{/repo}",
    "followers_url": "https://api.github.com/users/paultcochrane/followers",
    "url": "https://api.github.com/users/paultcochrane"
  },
  "updated_at": "2015-04-10T05:02:47Z",
  "created_at": "2015-04-10T04:55:50Z",
  "comments_url": "https://api.github.com/repos/perl6/doc/issues/73/comments",
  "pull_request": {
    "html_url": "https://github.com/perl6/doc/pull/73",
    "diff_url": "https://github.com/perl6/doc/pull/73.diff",
    "patch_url": "https://github.com/perl6/doc/pull/73.patch",
    "url": "https://api.github.com/repos/perl6/doc/pulls/73"
  },
  "locked": false,
  "title": "Update variables.pod",
  "id": 67509480,
  "html_url": "https://github.com/perl6/doc/pull/73",
  "closed_at": "2015-04-10T05:02:42Z",
  "milestone": null,
  "state": "closed",
  "labels_url": "https://api.github.com/repos/perl6/doc/issues/73/labels{/name}",
  "number": 73,
  "comments": 1,
  "labels": [
    
  ],
  "events_url": "https://api.github.com/repos/perl6/doc/issues/73/events",
  "user": {
    "following_url": "https://api.github.com/users/sjn/following{/other_user}",
    "node_id": "MDQ6VXNlcjU0NjM3",
    "gists_url": "https://api.github.com/users/sjn/gists{/gist_id}",
    "received_events_url": "https://api.github.com/users/sjn/received_events",
    "organizations_url": "https://api.github.com/users/sjn/orgs",
    "subscriptions_url": "https://api.github.com/users/sjn/subscriptions",
    "html_url": "https://github.com/sjn",
    "id": 54637,
    "login": "sjn",
    "type": "User",
    "repos_url": "https://api.github.com/users/sjn/repos",
    "site_admin": false,
    "events_url": "https://api.github.com/users/sjn/events{/privacy}",
    "gravatar_id": "",
    "avatar_url": "https://avatars3.githubusercontent.com/u/54637?v=4",
    "starred_url": "https://api.github.com/users/sjn/starred{/owner}{/repo}",
    "followers_url": "https://api.github.com/users/sjn/followers",
    "url": "https://api.github.com/users/sjn"
  },
  "repository_url": "https://api.github.com/repos/perl6/doc",
  "url": "https://api.github.com/repos/perl6/doc/issues/73"
}