{
  "body": "",
  "author_association": "MEMBER",
  "assignees": [
    
  ],
  "assignee": null,
  "closed_by": {
    "following_url": "https://api.github.com/users/tbrowder/following{/other_user}",
    "gists_url": "https://api.github.com/users/tbrowder/gists{/gist_id}",
    "received_events_url": "https://api.github.com/users/tbrowder/received_events",
    "organizations_url": "https://api.github.com/users/tbrowder/orgs",
    "subscriptions_url": "https://api.github.com/users/tbrowder/subscriptions",
    "html_url": "https://github.com/tbrowder",
    "id": 1039060,
    "login": "tbrowder",
    "type": "User",
    "repos_url": "https://api.github.com/users/tbrowder/repos",
    "site_admin": false,
    "events_url": "https://api.github.com/users/tbrowder/events{/privacy}",
    "gravatar_id": "",
    "avatar_url": "https://avatars0.githubusercontent.com/u/1039060?v=4",
    "starred_url": "https://api.github.com/users/tbrowder/starred{/owner}{/repo}",
    "followers_url": "https://api.github.com/users/tbrowder/followers",
    "url": "https://api.github.com/users/tbrowder"
  },
  "updated_at": "2016-08-31T15:38:20Z",
  "created_at": "2016-08-31T15:06:52Z",
  "comments_url": "https://api.github.com/repos/perl6/doc/issues/871/comments",
  "pull_request": {
    "html_url": "https://github.com/perl6/doc/pull/871",
    "diff_url": "https://github.com/perl6/doc/pull/871.diff",
    "patch_url": "https://github.com/perl6/doc/pull/871.patch",
    "url": "https://api.github.com/repos/perl6/doc/pulls/871"
  },
  "locked": false,
  "title": "add rudimentary doc on UInt",
  "id": 174298495,
  "html_url": "https://github.com/perl6/doc/pull/871",
  "closed_at": "2016-08-31T15:38:20Z",
  "milestone": null,
  "state": "closed",
  "labels_url": "https://api.github.com/repos/perl6/doc/issues/871/labels{/name}",
  "number": 871,
  "comments": 0,
  "labels": [
    
  ],
  "events_url": "https://api.github.com/repos/perl6/doc/issues/871/events",
  "user": {
    "following_url": "https://api.github.com/users/tbrowder/following{/other_user}",
    "gists_url": "https://api.github.com/users/tbrowder/gists{/gist_id}",
    "received_events_url": "https://api.github.com/users/tbrowder/received_events",
    "organizations_url": "https://api.github.com/users/tbrowder/orgs",
    "subscriptions_url": "https://api.github.com/users/tbrowder/subscriptions",
    "html_url": "https://github.com/tbrowder",
    "id": 1039060,
    "login": "tbrowder",
    "type": "User",
    "repos_url": "https://api.github.com/users/tbrowder/repos",
    "site_admin": false,
    "events_url": "https://api.github.com/users/tbrowder/events{/privacy}",
    "gravatar_id": "",
    "avatar_url": "https://avatars0.githubusercontent.com/u/1039060?v=4",
    "starred_url": "https://api.github.com/users/tbrowder/starred{/owner}{/repo}",
    "followers_url": "https://api.github.com/users/tbrowder/followers",
    "url": "https://api.github.com/users/tbrowder"
  },
  "repository_url": "https://api.github.com/repos/perl6/doc",
  "url": "https://api.github.com/repos/perl6/doc/issues/871"
}