{
  "closed_by": {
    "organizations_url": "https://api.github.com/users/AlexDaniel/orgs",
    "avatar_url": "https://avatars3.githubusercontent.com/u/5507503?v=4",
    "id": 5507503,
    "site_admin": false,
    "type": "User",
    "received_events_url": "https://api.github.com/users/AlexDaniel/received_events",
    "subscriptions_url": "https://api.github.com/users/AlexDaniel/subscriptions",
    "starred_url": "https://api.github.com/users/AlexDaniel/starred{/owner}{/repo}",
    "html_url": "https://github.com/AlexDaniel",
    "url": "https://api.github.com/users/AlexDaniel",
    "node_id": "MDQ6VXNlcjU1MDc1MDM=",
    "gravatar_id": "",
    "gists_url": "https://api.github.com/users/AlexDaniel/gists{/gist_id}",
    "following_url": "https://api.github.com/users/AlexDaniel/following{/other_user}",
    "followers_url": "https://api.github.com/users/AlexDaniel/followers",
    "events_url": "https://api.github.com/users/AlexDaniel/events{/privacy}",
    "repos_url": "https://api.github.com/users/AlexDaniel/repos",
    "login": "AlexDaniel"
  },
  "closed_at": "2017-11-05T11:57:00Z",
  "title": "Case-insensitive string comparison with lc/uc is probably a trap",
  "id": 185807236,
  "created_at": "2016-10-27T23:43:51Z",
  "user": {
    "organizations_url": "https://api.github.com/users/AlexDaniel/orgs",
    "avatar_url": "https://avatars3.githubusercontent.com/u/5507503?v=4",
    "id": 5507503,
    "site_admin": false,
    "type": "User",
    "received_events_url": "https://api.github.com/users/AlexDaniel/received_events",
    "subscriptions_url": "https://api.github.com/users/AlexDaniel/subscriptions",
    "starred_url": "https://api.github.com/users/AlexDaniel/starred{/owner}{/repo}",
    "html_url": "https://github.com/AlexDaniel",
    "url": "https://api.github.com/users/AlexDaniel",
    "node_id": "MDQ6VXNlcjU1MDc1MDM=",
    "gravatar_id": "",
    "gists_url": "https://api.github.com/users/AlexDaniel/gists{/gist_id}",
    "following_url": "https://api.github.com/users/AlexDaniel/following{/other_user}",
    "followers_url": "https://api.github.com/users/AlexDaniel/followers",
    "events_url": "https://api.github.com/users/AlexDaniel/events{/privacy}",
    "repos_url": "https://api.github.com/users/AlexDaniel/repos",
    "login": "AlexDaniel"
  },
  "locked": false,
  "node_id": "MDU6SXNzdWUxODU4MDcyMzY=",
  "html_url": "https://github.com/perl6/doc/issues/994",
  "url": "https://api.github.com/repos/perl6/doc/issues/994",
  "labels": [
    {
      "id": 244843225,
      "name": "docs",
      "url": "https://api.github.com/repos/perl6/doc/labels/docs",
      "node_id": "MDU6TGFiZWwyNDQ4NDMyMjU=",
      "default": false,
      "color": "5DE0FA"
    }
  ],
  "labels_url": "https://api.github.com/repos/perl6/doc/issues/994/labels{/name}",
  "author_association": "MEMBER",
  "assignee": null,
  "state": "closed",
  "comments_url": "https://api.github.com/repos/perl6/doc/issues/994/comments",
  "body": "``` perl6\nsay ‘groß’.lc eq ‘GROSS’.lc # False\nsay ‘groß’.uc eq ‘GROSS’.uc # True, but that's just luck\nsay ‘groß’.fc eq ‘GROSS’.fc # True\n```\n\nOf course, this is not specific to Perl 6. However, we probably want to mention it anyway given how much we love unicode.\n\n“Probably” because I'm not sure if there's someone who doesn't know about this.\n",
  "assignees": [
    
  ],
  "updated_at": "2017-11-05T11:57:00Z",
  "comments": 0,
  "milestone": null,
  "number": 994,
  "events_url": "https://api.github.com/repos/perl6/doc/issues/994/events",
  "repository_url": "https://api.github.com/repos/perl6/doc"
}